deafrica_tools/__init__.py
deafrica_tools/areaofinterest.py
deafrica_tools/bandindices.py
deafrica_tools/classification.py
deafrica_tools/coastal.py
deafrica_tools/dask.py
deafrica_tools/datahandling.py
deafrica_tools/externaldrive.py
deafrica_tools/get_config.py
deafrica_tools/load_africapolis.py
deafrica_tools/load_era5.py
deafrica_tools/load_isda.py
deafrica_tools/load_soil_moisture.py
deafrica_tools/load_wapor.py
deafrica_tools/plotting.py
deafrica_tools/spatial.py
deafrica_tools/temporal.py
deafrica_tools/waterbodies.py
deafrica_tools/wetlands.py
deafrica_tools/app/__init__.py
deafrica_tools/app/animations.py
deafrica_tools/app/changefilmstrips.py
deafrica_tools/app/crophealth.py
deafrica_tools/app/deacoastlines.py
deafrica_tools/app/forestmonitoring.py
deafrica_tools/app/geomedian.py
deafrica_tools/app/imageexport.py
deafrica_tools/app/planetbasemap.py
deafrica_tools/app/wetlandsinsighttool.py
deafrica_tools/app/widgetconstructors.py
deafrica_tools/locales/fr/LC_MESSAGES/deafrica_tools.mo
deafrica_tools/locales/fr/LC_MESSAGES/deafrica_tools.po
deafrica_tools-2.5.13.dist-info/licenses/LICENSE
deafrica_tools-2.5.13.dist-info/METADATA
deafrica_tools-2.5.13.dist-info/WHEEL
deafrica_tools-2.5.13.dist-info/top_level.txt
deafrica_tools-2.5.13.dist-info/RECORD
