Metadata-Version: 2.4
Name: deafrica-tools
Version: 2.5.13
Summary: Functions and algorithms for analysing Digital Earth Africa data.
Author-email: Digital Earth Africa <systems@digitalearthafrica.org>
Maintainer-email: Digital Earth Africa <systems@digitalearthafrica.org>
License:                                  Apache License
Project-URL: Homepage, https://github.com/digitalearthafrica/deafrica-sandbox-notebooks
Project-URL: Repository, https://github.com/digitalearthafrica/deafrica-sandbox-notebooks
Project-URL: Documentation, https://docs.digitalearthafrica.org/en/latest/sandbox/notebooks/Tools/index.html
Project-URL: Bug Tracker, https://github.com/digitalearthafrica/deafrica-sandbox-notebooks/issues
Classifier: License :: OSI Approved :: Apache Software License
Classifier: Programming Language :: Python
Classifier: Programming Language :: Python :: 3
Classifier: Programming Language :: Python :: 3.9
Classifier: Programming Language :: Python :: 3.10
Classifier: Programming Language :: Python :: 3.11
Classifier: Programming Language :: Python :: 3.12
Classifier: Intended Audience :: Science/Research
Classifier: Topic :: Scientific/Engineering :: GIS
Requires-Python: >=3.9
License-File: LICENSE
Requires-Dist: aiohttp
Requires-Dist: aiobotocore[boto3]
Requires-Dist: branca
Requires-Dist: dask[complete]
Requires-Dist: dask-ml
Requires-Dist: dask-gateway
Requires-Dist: datacube[performance,s3]
Requires-Dist: eo-tides
Requires-Dist: fiona
Requires-Dist: folium
Requires-Dist: fsspec
Requires-Dist: gdal
Requires-Dist: geojson
Requires-Dist: geopandas
Requires-Dist: geopy
Requires-Dist: hdstats
Requires-Dist: ipyleaflet
Requires-Dist: ipython
Requires-Dist: ipywidgets
Requires-Dist: joblib
Requires-Dist: localtileserver==0.10.3
Requires-Dist: rio-tiler==6.7.0
Requires-Dist: matplotlib
Requires-Dist: numexpr
Requires-Dist: numpy
Requires-Dist: odc-algo
Requires-Dist: odc-geo>=0.4.2
Requires-Dist: odc-ui
Requires-Dist: OWSLib
Requires-Dist: packaging
Requires-Dist: pandas
Requires-Dist: plotly
Requires-Dist: pydrive2[fsspec]
Requires-Dist: pyproj
Requires-Dist: pystac-client
Requires-Dist: python-dateutil
Requires-Dist: pytz
Requires-Dist: rasterio
Requires-Dist: rasterstats
Requires-Dist: requests
Requires-Dist: rioxarray
Requires-Dist: scikit-image
Requires-Dist: scikit-learn
Requires-Dist: scipy
Requires-Dist: seaborn
Requires-Dist: shapely
Requires-Dist: timescale
Requires-Dist: tqdm
Requires-Dist: xarray
Requires-Dist: gcsfs
Provides-Extra: tests
Requires-Dist: pytest; extra == "tests"
Provides-Extra: lint
Requires-Dist: black[jupyter]; extra == "lint"
Requires-Dist: flake8; extra == "lint"
Requires-Dist: isort>=5.0.0; extra == "lint"
Requires-Dist: pre-commit; extra == "lint"
Provides-Extra: dev
Requires-Dist: deafrica_tools[lint,tests]; extra == "dev"
Dynamic: license-file
